{"nodes": [{"id": "wavetable_horizon_canonical_svg", "label": "Wavetable Horizon Canonical Baseline SVG", "file_type": "image", "source_file": "tests/baselines/svg/wavetable-horizon-canonical.svg", "source_location": null, "source_url": null, "captured_at": null, "author": null, "contributor": null}], "edges": [{"source": "wavetable_horizon_canonical_svg", "target": "wavetable_algorithm", "relation": "references", "confidence": "EXTRACTED", "confidence_score": 0.98, "source_file": "tests/baselines/svg/wavetable-horizon-canonical.svg", "source_location": null, "weight": 1.0}, {"source": "wavetable_horizon_canonical_svg", "target": "visual_regression_test_suite", "relation": "references", "confidence": "EXTRACTED", "confidence_score": 0.98, "source_file": "tests/baselines/svg/wavetable-horizon-canonical.svg", "source_location": null, "weight": 1.0}, {"source": "wavetable_horizon_canonical_svg", "target": "svg_viewbox_320x220", "relation": "references", "confidence": "EXTRACTED", "confidence_score": 1.0, "source_file": "tests/baselines/svg/wavetable-horizon-canonical.svg", "source_location": null, "weight": 0.8}], "hyperedges": []}